{
  "id": "vorax/hybridvoraxmodelv4-arc-prize-2025",
  "title": "HybridVoraxModel V4 - ARC Prize 2025 (Corrected)", 
  "code_file": "vorax_repo/arc_model/hybridvoraxmodelv4-arc-prize-2025-corrected.ipynb",
  "language": "python",
  "kernel_type": "notebook", 
  "is_private": false,
  "enable_gpu": true,
  "enable_internet": true,
  "dataset_sources": ["abstraction-and-reasoning-prize"],
  "competition_sources": ["abstraction-and-reasoning-prize"],
  "keywords": ["deep learning", "optimization", "hybrid model", "pattern recognition"]
}